{
    "Innings1": {
        "BattingCard": [
            {
                "MatchID": "10540",
                "InningsNo": "1",
                "TeamID": "15",
                "PlayerID": "7",
                "PlayerName": "MURALI VIJAY ",
                "PlayerImage": null,
                "PlayingOrder": "1",
                "BowlerName": "bhuvneshwar kumar",
                "OutDesc": "c Naman Ojha b Bhuvneshwar Kumar",
                "Runs": "2",
                "Balls": "3",
                "DotBalls": "0",
                "DotBallPercentage": "0.00",
                "DotBallFrequency": "",
                "Ones": "0",
                "Twos": "0",
                "Threes": "0",
                "Fours": "0",
                "Sixes": "0",
                "BoundaryPercentage": "0.00",
                "BoundaryFrequency": "",
                "StrikeRate": "66.67",
                "MinOver": "0",
                "MinStrikerOver": "0",
                "WicketNo": null,
                "AgainstFast": "0",
                "AgainstSpin": "0",
                "AgainstFastPercent": "0.00",
                "AgainstSpinPercent": "0.00"
            },
            {
                "MatchID": "10540",
                "InningsNo": "1",
                "TeamID": "15",
                "PlayerID": "1085",
                "PlayerName": "MANAN VOHRA ",
                "PlayerImage": null,
                "PlayingOrder": "2",
                "BowlerName": "mustafizur rahman",
                "OutDesc": "run out (Shikhar Dhawan)",
                "Runs": "25",
                "Balls": "23",
                "DotBalls": "0",
                "DotBallPercentage": "0.00",
                "DotBallFrequency": "",
                "Ones": "0",
                "Twos": "0",
                "Threes": "0",
                "Fours": "3",
                "Sixes": "1",
                "BoundaryPercentage": "72.00",
                "BoundaryFrequency": "5.75",
                "StrikeRate": "108.70",
                "MinOver": "0",
                "MinStrikerOver": "0",
                "WicketNo": null,
                "AgainstFast": "0",
                "AgainstSpin": "0",
                "AgainstFastPercent": "0.00",
                "AgainstSpinPercent": "0.00"
            },
            {
                "MatchID": "10540",
                "InningsNo": "1",
                "TeamID": "15",
                "PlayerID": "191",
                "PlayerName": "SHAUN MARSH ",
                "PlayerImage": null,
                "PlayingOrder": "3",
                "BowlerName": "mustafizur rahman",
                "OutDesc": "lbw Mustafizur Rahman",
                "Runs": "40",
                "Balls": "34",
                "DotBalls": "0",
                "DotBallPercentage": "0.00",
                "DotBallFrequency": "",
                "Ones": "0",
                "Twos": "0",
                "Threes": "0",
                "Fours": "3",
                "Sixes": "2",
                "BoundaryPercentage": "60.00",
                "BoundaryFrequency": "6.80",
                "StrikeRate": "117.65",
                "MinOver": "0",
                "MinStrikerOver": "0",
                "WicketNo": null,
                "AgainstFast": "0",
                "AgainstSpin": "0",
                "AgainstFastPercent": "0.00",
                "AgainstSpinPercent": "0.00"
            },
            {
                "MatchID": "10540",
                "InningsNo": "1",
                "TeamID": "15",
                "PlayerID": "187",
                "PlayerName": "DAVID MILLER (C)",
                "PlayerImage": null,
                "PlayingOrder": "4",
                "BowlerName": "moises henriques",
                "OutDesc": "c Naman Ojha b Moises Henriques",
                "Runs": "9",
                "Balls": "11",
                "DotBalls": "0",
                "DotBallPercentage": "0.00",
                "DotBallFrequency": "",
                "Ones": "0",
                "Twos": "0",
                "Threes": "0",
                "Fours": "1",
                "Sixes": "0",
                "BoundaryPercentage": "44.44",
                "BoundaryFrequency": "11.00",
                "StrikeRate": "81.82",
                "MinOver": "0",
                "MinStrikerOver": "0",
                "WicketNo": null,
                "AgainstFast": "0",
                "AgainstSpin": "0",
                "AgainstFastPercent": "0.00",
                "AgainstSpinPercent": "0.00"
            },
            {
                "MatchID": "10540",
                "InningsNo": "1",
                "TeamID": "15",
                "PlayerID": "282",
                "PlayerName": "GLENN MAXWELL ",
                "PlayerImage": null,
                "PlayingOrder": "5",
                "BowlerName": "moises henriques",
                "OutDesc": "c Mustafizur Rahman b Moises Henriques",
                "Runs": "1",
                "Balls": "2",
                "DotBalls": "0",
                "DotBallPercentage": "0.00",
                "DotBallFrequency": "",
                "Ones": "0",
                "Twos": "0",
                "Threes": "0",
                "Fours": "0",
                "Sixes": "0",
                "BoundaryPercentage": "0.00",
                "BoundaryFrequency": "",
                "StrikeRate": "50.00",
                "MinOver": "0",
                "MinStrikerOver": "0",
                "WicketNo": null,
                "AgainstFast": "0",
                "AgainstSpin": "0",
                "AgainstFastPercent": "0.00",
                "AgainstSpinPercent": "0.00"
            },
            {
                "MatchID": "10540",
                "InningsNo": "1",
                "TeamID": "15",
                "PlayerID": "2732",
                "PlayerName": "NIKHIL NAIK (WK)",
                "PlayerImage": null,
                "PlayingOrder": "6",
                "BowlerName": "mustafizur rahman",
                "OutDesc": "c Moises Henriques b Mustafizur Rahman",
                "Runs": "22",
                "Balls": "28",
                "DotBalls": "0",
                "DotBallPercentage": "0.00",
                "DotBallFrequency": "",
                "Ones": "0",
                "Twos": "0",
                "Threes": "0",
                "Fours": "1",
                "Sixes": "0",
                "BoundaryPercentage": "18.18",
                "BoundaryFrequency": "28.00",
                "StrikeRate": "78.57",
                "MinOver": "0",
                "MinStrikerOver": "0",
                "WicketNo": null,
                "AgainstFast": "0",
                "AgainstSpin": "0",
                "AgainstFastPercent": "0.00",
                "AgainstSpinPercent": "0.00"
            },
            {
                "MatchID": "10540",
                "InningsNo": "1",
                "TeamID": "15",
                "PlayerID": "1113",
                "PlayerName": "AXAR PATEL ",
                "PlayerImage": null,
                "PlayingOrder": "7",
                "BowlerName": "",
                "OutDesc": "not out",
                "Runs": "36",
                "Balls": "17",
                "DotBalls": "0",
                "DotBallPercentage": "0.00",
                "DotBallFrequency": "",
                "Ones": "0",
                "Twos": "0",
                "Threes": "0",
                "Fours": "1",
                "Sixes": "3",
                "BoundaryPercentage": "61.11",
                "BoundaryFrequency": "4.25",
                "StrikeRate": "211.76",
                "MinOver": "0",
                "MinStrikerOver": "0",
                "WicketNo": null,
                "AgainstFast": "0",
                "AgainstSpin": "0",
                "AgainstFastPercent": "0.00",
                "AgainstSpinPercent": "0.00"
            },
            {
                "MatchID": "10540",
                "InningsNo": "1",
                "TeamID": "15",
                "PlayerID": "1088",
                "PlayerName": "RISHI DHAWAN ",
                "PlayerImage": null,
                "PlayingOrder": "8",
                "BowlerName": "",
                "OutDesc": "not out",
                "Runs": "3",
                "Balls": "2",
                "DotBalls": "0",
                "DotBallPercentage": "0.00",
                "DotBallFrequency": "",
                "Ones": "0",
                "Twos": "0",
                "Threes": "0",
                "Fours": "0",
                "Sixes": "0",
                "BoundaryPercentage": "0.00",
                "BoundaryFrequency": "",
                "StrikeRate": "150.00",
                "MinOver": "0",
                "MinStrikerOver": "0",
                "WicketNo": null,
                "AgainstFast": "0",
                "AgainstSpin": "0",
                "AgainstFastPercent": "0.00",
                "AgainstSpinPercent": "0.00"
            }
        ],
        "Extras": [
            {
                "MatchID": "10540",
                "InningsNo": "1",
                "TeamID": "15",
                "Total": "143/6 (20 Overs)",
                "TotalExtras": "5",
                "Byes": "0",
                "LegByes": "1",
                "NoBalls": "0",
                "Wides": "4",
                "Penalty": "0",
                "CurrentRunRate": "7.15",
                "FallScore": "143",
                "FallWickets": "6",
                "FallOvers": "20",
                "BattingTeamName": "Punjab Kings",
                "BowlingTeamName": "Sunrisers Hyderabad",
                "MaxPartnerShipRuns": ""
            }
        ],
        "FallOfWickets": [
            {
                "MatchID": "10540",
                "InningsNo": "1",
                "TeamID": "15",
                "PlayerID": "7",
                "PlayerName": "MURALI VIJAY",
                "Score": "14/1(3.1)",
                "FallScore": "14",
                "FallWickets": "1",
                "FallOvers": "3.1"
            },
            {
                "MatchID": "10540",
                "InningsNo": "1",
                "TeamID": "15",
                "PlayerID": "1085",
                "PlayerName": "MANAN VOHRA",
                "Score": "35/2(6.5)",
                "FallScore": "35",
                "FallWickets": "2",
                "FallOvers": "6.5"
            },
            {
                "MatchID": "10540",
                "InningsNo": "1",
                "TeamID": "15",
                "PlayerID": "187",
                "PlayerName": "DAVID MILLER",
                "Score": "63/3(10.2)",
                "FallScore": "63",
                "FallWickets": "3",
                "FallOvers": "10.2"
            },
            {
                "MatchID": "10540",
                "InningsNo": "1",
                "TeamID": "15",
                "PlayerID": "282",
                "PlayerName": "GLENN MAXWELL",
                "Score": "65/4(10.6)",
                "FallScore": "65",
                "FallWickets": "4",
                "FallOvers": "10.6"
            },
            {
                "MatchID": "10540",
                "InningsNo": "1",
                "TeamID": "15",
                "PlayerID": "191",
                "PlayerName": "SHAUN MARSH",
                "Score": "89/5(14.3)",
                "FallScore": "89",
                "FallWickets": "5",
                "FallOvers": "14.3"
            },
            {
                "MatchID": "10540",
                "InningsNo": "1",
                "TeamID": "15",
                "PlayerID": "2732",
                "PlayerName": "NIKHIL NAIK",
                "Score": "139/6(20.2)",
                "FallScore": "139",
                "FallWickets": "6",
                "FallOvers": "20.2"
            }
        ],
        "WagonWheel": [
            {
                "BallID": "0",
                "StrikerID": "0",
                "BowlerID": "0",
                "FielderAngle": "0",
                "FielderLengthRation": "0",
                "Runs": "0",
                "BatType": "0",
                "IsFour": "0",
                "IsSix": "0"
            }
        ],
        "PartnershipScores": [
            {
                "MatchID": "0",
                "BattingTeamID": "0",
                "InningsNo": "0",
                "StrikerID": "0",
                "Striker": "0",
                "NonStrikerID": "0",
                "NonStriker": "0",
                "PartnershipTotal": "0",
                "StrikerRuns": "0",
                "StrikerBalls": "0",
                "Extras": "0",
                "NonStrikerRuns": "0",
                "NonStrikerBalls": "0",
                "MatchMaxOver": "0",
                "MatchMinOver": "0"
            }
        ],
        "PartnershipBreak": [
            {
                "InningsNo": "0",
                "OverNo": "0",
                "WicketNo": "0",
                "WicketType": "0",
                "OutBatsmanID": "0"
            }
        ],
        "BowlingCard": [
            {
                "MatchID": "10540",
                "InningsNo": "1",
                "TeamID": "20",
                "PlayerID": "116",
                "PlayerName": "Bhuvneshwar Kumar",
                "PlayerImageName": null,
                "PlayerImage": null,
                "Overs": "4.0",
                "Maidens": "0",
                "Runs": "37",
                "Wickets": "1",
                "Wides": "0",
                "NoBalls": "0",
                "Economy": "9.25",
                "BowlingOrder": "1",
                "TotalLegalBallsBowled": null,
                "ScoringBalls": null,
                "DotBalls": "7",
                "DBPercent": "0",
                "DBFrequency": "0",
                "Ones": null,
                "Twos": null,
                "Threes": null,
                "Fours": null,
                "Sixes": null,
                "BdryPercent": "0",
                "BdryFreq": "0",
                "StrikeRate": "0",
                "FourPercent": "0",
                "SixPercent": "0"
            },
            {
                "MatchID": "10540",
                "InningsNo": "1",
                "TeamID": "20",
                "PlayerID": "2746",
                "PlayerName": "Barinder Sran",
                "PlayerImageName": null,
                "PlayerImage": null,
                "Overs": "4.0",
                "Maidens": "0",
                "Runs": "33",
                "Wickets": "0",
                "Wides": "0",
                "NoBalls": "0",
                "Economy": "8.25",
                "BowlingOrder": "2",
                "TotalLegalBallsBowled": null,
                "ScoringBalls": null,
                "DotBalls": "6",
                "DBPercent": "0",
                "DBFrequency": "0",
                "Ones": null,
                "Twos": null,
                "Threes": null,
                "Fours": null,
                "Sixes": null,
                "BdryPercent": "0",
                "BdryFreq": "0",
                "StrikeRate": "0",
                "FourPercent": "0",
                "SixPercent": "0"
            },
            {
                "MatchID": "10540",
                "InningsNo": "1",
                "TeamID": "20",
                "PlayerID": "1556",
                "PlayerName": "Deepak Hooda",
                "PlayerImageName": null,
                "PlayerImage": null,
                "Overs": "4.0",
                "Maidens": "0",
                "Runs": "30",
                "Wickets": "0",
                "Wides": "2",
                "NoBalls": "0",
                "Economy": "7.50",
                "BowlingOrder": "3",
                "TotalLegalBallsBowled": null,
                "ScoringBalls": null,
                "DotBalls": "11",
                "DBPercent": "0",
                "DBFrequency": "0",
                "Ones": null,
                "Twos": null,
                "Threes": null,
                "Fours": null,
                "Sixes": null,
                "BdryPercent": "0",
                "BdryFreq": "0",
                "StrikeRate": "0",
                "FourPercent": "0",
                "SixPercent": "0"
            },
            {
                "MatchID": "10540",
                "InningsNo": "1",
                "TeamID": "20",
                "PlayerID": "1594",
                "PlayerName": "Mustafizur Rahman",
                "PlayerImageName": null,
                "PlayerImage": null,
                "Overs": "4.0",
                "Maidens": "1",
                "Runs": "9",
                "Wickets": "2",
                "Wides": "0",
                "NoBalls": "0",
                "Economy": "2.25",
                "BowlingOrder": "4",
                "TotalLegalBallsBowled": null,
                "ScoringBalls": null,
                "DotBalls": "17",
                "DBPercent": "0",
                "DBFrequency": "0",
                "Ones": null,
                "Twos": null,
                "Threes": null,
                "Fours": null,
                "Sixes": null,
                "BdryPercent": "0",
                "BdryFreq": "0",
                "StrikeRate": "0",
                "FourPercent": "0",
                "SixPercent": "0"
            },
            {
                "MatchID": "10540",
                "InningsNo": "1",
                "TeamID": "20",
                "PlayerID": "388",
                "PlayerName": "Moises Henriques",
                "PlayerImageName": null,
                "PlayerImage": null,
                "Overs": "4.0",
                "Maidens": "0",
                "Runs": "33",
                "Wickets": "2",
                "Wides": "1",
                "NoBalls": "0",
                "Economy": "8.25",
                "BowlingOrder": "5",
                "TotalLegalBallsBowled": null,
                "ScoringBalls": null,
                "DotBalls": "7",
                "DBPercent": "0",
                "DBFrequency": "0",
                "Ones": null,
                "Twos": null,
                "Threes": null,
                "Fours": null,
                "Sixes": null,
                "BdryPercent": "0",
                "BdryFreq": "0",
                "StrikeRate": "0",
                "FourPercent": "0",
                "SixPercent": "0"
            }
        ],
        "ManhattanGraph": [
            {
                "InningsNo": "0",
                "OverNo": "0",
                "BattingTeamID": "0",
                "OverRuns": "0",
                "BowlerRuns": "0",
                "BowlerID": "0",
                "Wickets": "0",
                "Bowler": "0"
            }
        ],
        "ManhattanWickets": [],
        "OverHistory": [
            {
                "BallID": "0",
                "MatchID": "0",
                "InningsNo": "0",
                "BattingTeamID": "0",
                "TeamName": "0",
                "StrikerID": "0",
                "NonStrikerID": "0",
                "BatsManName": "0",
                "BowlerID": "0",
                "BowlerName": "0",
                "BowlerType": "0",
                "OverNO": "0",
                "OverName": "0",
                "BallNo": "0",
                "Runs": "0",
                "BallRuns": "0",
                "RunsText": "0",
                "ActualRuns": "0",
                "IsOne": "0",
                "IsTwo": "0",
                "IsThree": "0",
                "IsDotball": "0",
                "BallCount": "0",
                "Extras": "0",
                "IsWide": "0",
                "IsNoBall": "0",
                "IsBye": "0",
                "IsLegBye": "0",
                "IsFour": "0",
                "IsSix": "0",
                "IsWicket": "0",
                "Wickets": "0",
                "VideoFile": "0",
                "CommentOver": "0",
                "BallName": "0",
                "CommentStrikers": "0",
                "Commentry": "0",
                "IsMaiden": "0",
                "IsExtra": "0",
                "OutBatsManID": "0",
                "WicketType": "0",
                "TotalRuns": "0",
                "TotalWickets": "0",
                "Xpitch": "0",
                "Ypitch": "0"
            }
        ],
        "WagonWheelSummary": [
            {
                "MatchID": "10540",
                "BattingTeamID": "15",
                "InningsNo": "1",
                "Ones": "0",
                "Twos": "0",
                "Threes": "0",
                "Fours": "9",
                "Sixes": "6"
            }
        ],
        "battingheadtohead": [],
        "bowlingheadtohead": []
    },
    "Innings2": {
        "BattingCard": [
            {
                "MatchID": "10540",
                "InningsNo": "2",
                "TeamID": "20",
                "PlayerID": "170",
                "PlayerName": "DAVID WARNER (C)",
                "PlayerImage": null,
                "PlayingOrder": "1",
                "BowlerName": "sandeep sharma",
                "OutDesc": "c David Miller b Sandeep Sharma",
                "Runs": "59",
                "Balls": "31",
                "DotBalls": "0",
                "DotBallPercentage": "0.00",
                "DotBallFrequency": "",
                "Ones": "0",
                "Twos": "0",
                "Threes": "0",
                "Fours": "7",
                "Sixes": "3",
                "BoundaryPercentage": "77.97",
                "BoundaryFrequency": "3.10",
                "StrikeRate": "190.32",
                "MinOver": "0",
                "MinStrikerOver": "0",
                "WicketNo": null,
                "AgainstFast": "0",
                "AgainstSpin": "0",
                "AgainstFastPercent": "0.00",
                "AgainstSpinPercent": "0.00"
            },
            {
                "MatchID": "10540",
                "InningsNo": "2",
                "TeamID": "20",
                "PlayerID": "41",
                "PlayerName": "SHIKHAR DHAWAN ",
                "PlayerImage": null,
                "PlayingOrder": "2",
                "BowlerName": "rishi dhawan",
                "OutDesc": "c Nikhil Naik b Rishi Dhawan",
                "Runs": "45",
                "Balls": "44",
                "DotBalls": "0",
                "DotBallPercentage": "0.00",
                "DotBallFrequency": "",
                "Ones": "0",
                "Twos": "0",
                "Threes": "0",
                "Fours": "4",
                "Sixes": "0",
                "BoundaryPercentage": "35.56",
                "BoundaryFrequency": "11.00",
                "StrikeRate": "102.27",
                "MinOver": "0",
                "MinStrikerOver": "0",
                "WicketNo": null,
                "AgainstFast": "0",
                "AgainstSpin": "0",
                "AgainstFastPercent": "0.00",
                "AgainstSpinPercent": "0.00"
            },
            {
                "MatchID": "10540",
                "InningsNo": "2",
                "TeamID": "20",
                "PlayerID": "99",
                "PlayerName": "ADITYA TARE ",
                "PlayerImage": null,
                "PlayingOrder": "3",
                "BowlerName": "sandeep sharma",
                "OutDesc": "run out (David Miller)",
                "Runs": "0",
                "Balls": "1",
                "DotBalls": "0",
                "DotBallPercentage": "0.00",
                "DotBallFrequency": "",
                "Ones": "0",
                "Twos": "0",
                "Threes": "0",
                "Fours": "0",
                "Sixes": "0",
                "BoundaryPercentage": "",
                "BoundaryFrequency": "",
                "StrikeRate": "0.00",
                "MinOver": "0",
                "MinStrikerOver": "0",
                "WicketNo": null,
                "AgainstFast": "0",
                "AgainstSpin": "0",
                "AgainstFastPercent": "0.00",
                "AgainstSpinPercent": "0.00"
            },
            {
                "MatchID": "10540",
                "InningsNo": "2",
                "TeamID": "20",
                "PlayerID": "197",
                "PlayerName": "EOIN MORGAN ",
                "PlayerImage": null,
                "PlayingOrder": "4",
                "BowlerName": "mohit sharma",
                "OutDesc": "c Manan Vohra b Mohit Sharma",
                "Runs": "25",
                "Balls": "20",
                "DotBalls": "0",
                "DotBallPercentage": "0.00",
                "DotBallFrequency": "",
                "Ones": "0",
                "Twos": "0",
                "Threes": "0",
                "Fours": "2",
                "Sixes": "1",
                "BoundaryPercentage": "56.00",
                "BoundaryFrequency": "6.67",
                "StrikeRate": "125.00",
                "MinOver": "0",
                "MinStrikerOver": "0",
                "WicketNo": null,
                "AgainstFast": "0",
                "AgainstSpin": "0",
                "AgainstFastPercent": "0.00",
                "AgainstSpinPercent": "0.00"
            },
            {
                "MatchID": "10540",
                "InningsNo": "2",
                "TeamID": "20",
                "PlayerID": "1556",
                "PlayerName": "DEEPAK HOODA ",
                "PlayerImage": null,
                "PlayingOrder": "5",
                "BowlerName": "mohit sharma",
                "OutDesc": "run out (David Miller)",
                "Runs": "5",
                "Balls": "5",
                "DotBalls": "0",
                "DotBallPercentage": "0.00",
                "DotBallFrequency": "",
                "Ones": "0",
                "Twos": "0",
                "Threes": "0",
                "Fours": "0",
                "Sixes": "0",
                "BoundaryPercentage": "0.00",
                "BoundaryFrequency": "",
                "StrikeRate": "100.00",
                "MinOver": "0",
                "MinStrikerOver": "0",
                "WicketNo": null,
                "AgainstFast": "0",
                "AgainstSpin": "0",
                "AgainstFastPercent": "0.00",
                "AgainstSpinPercent": "0.00"
            },
            {
                "MatchID": "10540",
                "InningsNo": "2",
                "TeamID": "20",
                "PlayerID": "388",
                "PlayerName": "MOISES HENRIQUES ",
                "PlayerImage": null,
                "PlayingOrder": "6",
                "BowlerName": "",
                "OutDesc": "not out",
                "Runs": "5",
                "Balls": "4",
                "DotBalls": "0",
                "DotBallPercentage": "0.00",
                "DotBallFrequency": "",
                "Ones": "0",
                "Twos": "0",
                "Threes": "0",
                "Fours": "1",
                "Sixes": "0",
                "BoundaryPercentage": "80.00",
                "BoundaryFrequency": "4.00",
                "StrikeRate": "125.00",
                "MinOver": "0",
                "MinStrikerOver": "0",
                "WicketNo": null,
                "AgainstFast": "0",
                "AgainstSpin": "0",
                "AgainstFastPercent": "0.00",
                "AgainstSpinPercent": "0.00"
            },
            {
                "MatchID": "10540",
                "InningsNo": "2",
                "TeamID": "20",
                "PlayerID": "52",
                "PlayerName": "NAMAN OJHA (WK)",
                "PlayerImage": null,
                "PlayingOrder": "7",
                "BowlerName": "",
                "OutDesc": "not out",
                "Runs": "2",
                "Balls": "2",
                "DotBalls": "0",
                "DotBallPercentage": "0.00",
                "DotBallFrequency": "",
                "Ones": "0",
                "Twos": "0",
                "Threes": "0",
                "Fours": "0",
                "Sixes": "0",
                "BoundaryPercentage": "0.00",
                "BoundaryFrequency": "",
                "StrikeRate": "100.00",
                "MinOver": "0",
                "MinStrikerOver": "0",
                "WicketNo": null,
                "AgainstFast": "0",
                "AgainstSpin": "0",
                "AgainstFastPercent": "0.00",
                "AgainstSpinPercent": "0.00"
            }
        ],
        "Extras": [
            {
                "MatchID": "10540",
                "InningsNo": "2",
                "TeamID": "20",
                "Total": "146/5 (17.5 Overs)",
                "TotalExtras": "5",
                "Byes": "0",
                "LegByes": "0",
                "NoBalls": "0",
                "Wides": "5",
                "Penalty": "0",
                "CurrentRunRate": "8.18",
                "FallScore": "146",
                "FallWickets": "5",
                "FallOvers": "17.5",
                "BattingTeamName": "Sunrisers Hyderabad",
                "BowlingTeamName": "Punjab Kings",
                "MaxPartnerShipRuns": ""
            }
        ],
        "FallOfWickets": [
            {
                "MatchID": "10540",
                "InningsNo": "2",
                "TeamID": "20",
                "PlayerID": "170",
                "PlayerName": "DAVID WARNER",
                "Score": "90/1(10.5)",
                "FallScore": "90",
                "FallWickets": "1",
                "FallOvers": "10.5"
            },
            {
                "MatchID": "10540",
                "InningsNo": "2",
                "TeamID": "20",
                "PlayerID": "99",
                "PlayerName": "ADITYA TARE",
                "Score": "90/2(10.6)",
                "FallScore": "90",
                "FallWickets": "2",
                "FallOvers": "10.6"
            },
            {
                "MatchID": "10540",
                "InningsNo": "2",
                "TeamID": "20",
                "PlayerID": "41",
                "PlayerName": "SHIKHAR DHAWAN",
                "Score": "115/3(14.6)",
                "FallScore": "115",
                "FallWickets": "3",
                "FallOvers": "14.6"
            },
            {
                "MatchID": "10540",
                "InningsNo": "2",
                "TeamID": "20",
                "PlayerID": "197",
                "PlayerName": "EOIN MORGAN",
                "Score": "139/4(17.5)",
                "FallScore": "139",
                "FallWickets": "4",
                "FallOvers": "17.5"
            },
            {
                "MatchID": "10540",
                "InningsNo": "2",
                "TeamID": "20",
                "PlayerID": "1556",
                "PlayerName": "DEEPAK HOODA",
                "Score": "139/5(17.6)",
                "FallScore": "139",
                "FallWickets": "5",
                "FallOvers": "17.6"
            }
        ],
        "WagonWheel": [
            {
                "BallID": "0",
                "StrikerID": "0",
                "BowlerID": "0",
                "FielderAngle": "0",
                "FielderLengthRation": "0",
                "Runs": "0",
                "BatType": "0",
                "IsFour": "0",
                "IsSix": "0"
            }
        ],
        "PartnershipScores": [
            {
                "MatchID": "0",
                "BattingTeamID": "0",
                "InningsNo": "0",
                "StrikerID": "0",
                "Striker": "0",
                "NonStrikerID": "0",
                "NonStriker": "0",
                "PartnershipTotal": "0",
                "StrikerRuns": "0",
                "StrikerBalls": "0",
                "Extras": "0",
                "NonStrikerRuns": "0",
                "NonStrikerBalls": "0",
                "MatchMaxOver": "0",
                "MatchMinOver": "0"
            }
        ],
        "PartnershipBreak": [
            {
                "InningsNo": "0",
                "OverNo": "0",
                "WicketNo": "0",
                "WicketType": "0",
                "OutBatsmanID": "0"
            }
        ],
        "BowlingCard": [
            {
                "MatchID": "10540",
                "InningsNo": "2",
                "TeamID": "15",
                "PlayerID": "1112",
                "PlayerName": "Sandeep Sharma",
                "PlayerImageName": null,
                "PlayerImage": null,
                "Overs": "4.0",
                "Maidens": "0",
                "Runs": "30",
                "Wickets": "1",
                "Wides": "0",
                "NoBalls": "0",
                "Economy": "7.50",
                "BowlingOrder": "1",
                "TotalLegalBallsBowled": null,
                "ScoringBalls": null,
                "DotBalls": "12",
                "DBPercent": "0",
                "DBFrequency": "0",
                "Ones": null,
                "Twos": null,
                "Threes": null,
                "Fours": null,
                "Sixes": null,
                "BdryPercent": "0",
                "BdryFreq": "0",
                "StrikeRate": "0",
                "FourPercent": "0",
                "SixPercent": "0"
            },
            {
                "MatchID": "10540",
                "InningsNo": "2",
                "TeamID": "15",
                "PlayerID": "1105",
                "PlayerName": "Kyle Abbott",
                "PlayerImageName": null,
                "PlayerImage": null,
                "Overs": "3.0",
                "Maidens": "0",
                "Runs": "34",
                "Wickets": "0",
                "Wides": "0",
                "NoBalls": "0",
                "Economy": "11.33",
                "BowlingOrder": "2",
                "TotalLegalBallsBowled": null,
                "ScoringBalls": null,
                "DotBalls": "4",
                "DBPercent": "0",
                "DBFrequency": "0",
                "Ones": null,
                "Twos": null,
                "Threes": null,
                "Fours": null,
                "Sixes": null,
                "BdryPercent": "0",
                "BdryFreq": "0",
                "StrikeRate": "0",
                "FourPercent": "0",
                "SixPercent": "0"
            },
            {
                "MatchID": "10540",
                "InningsNo": "2",
                "TeamID": "15",
                "PlayerID": "282",
                "PlayerName": "Glenn Maxwell",
                "PlayerImageName": null,
                "PlayerImage": null,
                "Overs": "2.0",
                "Maidens": "0",
                "Runs": "16",
                "Wickets": "0",
                "Wides": "0",
                "NoBalls": "0",
                "Economy": "8.00",
                "BowlingOrder": "3",
                "TotalLegalBallsBowled": null,
                "ScoringBalls": null,
                "DotBalls": "4",
                "DBPercent": "0",
                "DBFrequency": "0",
                "Ones": null,
                "Twos": null,
                "Threes": null,
                "Fours": null,
                "Sixes": null,
                "BdryPercent": "0",
                "BdryFreq": "0",
                "StrikeRate": "0",
                "FourPercent": "0",
                "SixPercent": "0"
            },
            {
                "MatchID": "10540",
                "InningsNo": "2",
                "TeamID": "15",
                "PlayerID": "1107",
                "PlayerName": "Mohit Sharma",
                "PlayerImageName": null,
                "PlayerImage": null,
                "Overs": "3.0",
                "Maidens": "0",
                "Runs": "20",
                "Wickets": "1",
                "Wides": "3",
                "NoBalls": "0",
                "Economy": "6.66",
                "BowlingOrder": "4",
                "TotalLegalBallsBowled": null,
                "ScoringBalls": null,
                "DotBalls": "8",
                "DBPercent": "0",
                "DBFrequency": "0",
                "Ones": null,
                "Twos": null,
                "Threes": null,
                "Fours": null,
                "Sixes": null,
                "BdryPercent": "0",
                "BdryFreq": "0",
                "StrikeRate": "0",
                "FourPercent": "0",
                "SixPercent": "0"
            },
            {
                "MatchID": "10540",
                "InningsNo": "2",
                "TeamID": "15",
                "PlayerID": "1088",
                "PlayerName": "Rishi Dhawan",
                "PlayerImageName": null,
                "PlayerImage": null,
                "Overs": "4.0",
                "Maidens": "0",
                "Runs": "35",
                "Wickets": "1",
                "Wides": "2",
                "NoBalls": "0",
                "Economy": "8.75",
                "BowlingOrder": "5",
                "TotalLegalBallsBowled": null,
                "ScoringBalls": null,
                "DotBalls": "7",
                "DBPercent": "0",
                "DBFrequency": "0",
                "Ones": null,
                "Twos": null,
                "Threes": null,
                "Fours": null,
                "Sixes": null,
                "BdryPercent": "0",
                "BdryFreq": "0",
                "StrikeRate": "0",
                "FourPercent": "0",
                "SixPercent": "0"
            },
            {
                "MatchID": "10540",
                "InningsNo": "2",
                "TeamID": "15",
                "PlayerID": "1113",
                "PlayerName": "Axar Patel",
                "PlayerImageName": null,
                "PlayerImage": null,
                "Overs": "1.5",
                "Maidens": "0",
                "Runs": "11",
                "Wickets": "0",
                "Wides": "0",
                "NoBalls": "0",
                "Economy": "6.00",
                "BowlingOrder": "6",
                "TotalLegalBallsBowled": null,
                "ScoringBalls": null,
                "DotBalls": "4",
                "DBPercent": "0",
                "DBFrequency": "0",
                "Ones": null,
                "Twos": null,
                "Threes": null,
                "Fours": null,
                "Sixes": null,
                "BdryPercent": "0",
                "BdryFreq": "0",
                "StrikeRate": "0",
                "FourPercent": "0",
                "SixPercent": "0"
            }
        ],
        "ManhattanGraph": [
            {
                "InningsNo": "0",
                "OverNo": "0",
                "BattingTeamID": "0",
                "OverRuns": "0",
                "BowlerRuns": "0",
                "BowlerID": "0",
                "Wickets": "0",
                "Bowler": "0"
            }
        ],
        "ManhattanWickets": [],
        "OverHistory": [
            {
                "BallID": "0",
                "MatchID": "0",
                "InningsNo": "0",
                "BattingTeamID": "0",
                "TeamName": "0",
                "StrikerID": "0",
                "NonStrikerID": "0",
                "BatsManName": "0",
                "BowlerID": "0",
                "BowlerName": "0",
                "BowlerType": "0",
                "OverNO": "0",
                "OverName": "0",
                "BallNo": "0",
                "Runs": "0",
                "BallRuns": "0",
                "RunsText": "0",
                "ActualRuns": "0",
                "IsOne": "0",
                "IsTwo": "0",
                "IsThree": "0",
                "IsDotball": "0",
                "BallCount": "0",
                "Extras": "0",
                "IsWide": "0",
                "IsNoBall": "0",
                "IsBye": "0",
                "IsLegBye": "0",
                "IsFour": "0",
                "IsSix": "0",
                "IsWicket": "0",
                "Wickets": "0",
                "VideoFile": "0",
                "CommentOver": "0",
                "BallName": "0",
                "CommentStrikers": "0",
                "Commentry": "0",
                "IsMaiden": "0",
                "IsExtra": "0",
                "OutBatsManID": "0",
                "WicketType": "0",
                "TotalRuns": "0",
                "TotalWickets": "0",
                "Xpitch": "0",
                "Ypitch": "0"
            }
        ],
        "WagonWheelSummary": [
            {
                "MatchID": "10540",
                "BattingTeamID": "20",
                "InningsNo": "2",
                "Ones": "0",
                "Twos": "0",
                "Threes": "0",
                "Fours": "14",
                "Sixes": "4"
            }
        ],
        "battingheadtohead": [],
        "bowlingheadtohead": []
    }
}